__init__.py
novactl/__init__.py
novactl/auth.py
novactl/config.py
novactl/config_schema.json
novactl/main.py
novactl-0.1.1.dist-info/licenses/LICENSE
novactl-0.1.1.dist-info/METADATA
novactl-0.1.1.dist-info/WHEEL
novactl-0.1.1.dist-info/entry_points.txt
novactl-0.1.1.dist-info/top_level.txt
novactl-0.1.1.dist-info/RECORD
