Metadata-Version: 2.4
Name: novactl
Version: 0.1.1
Summary: Boilerplate CLI with Keycloak/OAuth2 Device Flow Authentication using Typer and Rich.
Author-email: Harsha Krishnareddy <c0mpiler@ins8s.dev>
License: MIT License
Project-URL: Homepage, https://github.com/c0mpiler/novactl
Project-URL: Repository, https://github.com/c0mpiler/novactl
Project-URL: Bug Tracker, https://github.com/c0mpiler/novactl/issues
Keywords: cli,typer,rich,keycloak,oauth2,oidc,authentication,boilerplate,template,python,keyring,device flow,oauth,command line,security,developer tools
Classifier: Development Status :: 4 - Beta
Classifier: Programming Language :: Python :: 3
Classifier: Programming Language :: Python :: 3.8
Classifier: Programming Language :: Python :: 3.9
Classifier: Programming Language :: Python :: 3.10
Classifier: Programming Language :: Python :: 3.11
Classifier: License :: OSI Approved :: MIT License
Classifier: Operating System :: OS Independent
Classifier: Intended Audience :: Developers
Classifier: Topic :: Software Development :: Libraries :: Python Modules
Classifier: Topic :: Software Development :: User Interfaces
Classifier: Topic :: Security
Classifier: Topic :: Utilities
Classifier: Typing :: Typed
Requires-Python: >=3.8
License-File: LICENSE
Requires-Dist: typer[all]>=0.9.0
Requires-Dist: rich>=13.0.0
Requires-Dist: requests>=2.28.0
Requires-Dist: python-jose[cryptography]>=3.3.0
Requires-Dist: keyring>=23.0.0
Requires-Dist: PyYAML>=6.0
Requires-Dist: jsonschema>=4.0.0
Requires-Dist: urllib3>=1.26.0
Provides-Extra: test
Requires-Dist: pytest>=7.0.0; extra == "test"
Requires-Dist: pytest-cov>=4.0.0; extra == "test"
Requires-Dist: requests-mock>=1.9.0; extra == "test"
Requires-Dist: pyfakefs>=5.0.0; extra == "test"
Requires-Dist: cryptography; extra == "test"
Provides-Extra: dev
Requires-Dist: novactl[test]; extra == "dev"
Requires-Dist: black; extra == "dev"
Requires-Dist: flake8; extra == "dev"
Requires-Dist: mypy; extra == "dev"
Requires-Dist: isort; extra == "dev"
Requires-Dist: types-PyYAML; extra == "dev"
Requires-Dist: types-requests; extra == "dev"
Requires-Dist: types-jsonschema; extra == "dev"
Requires-Dist: pre-commit; extra == "dev"
Requires-Dist: deptry; extra == "dev"
Dynamic: license-file
